autoansign/__init__.py
autoansign/app_alicloud.py
autoansign/run.py
autoansign/web_ablesci.py
autoansign/web_muchong.py
autoansign/web_tiyanbi.py
autoansign/web_url.py
autoansign/assets/tpl1724917379162.png
autoansign/assets/tpl1724918907933.png
autoansign/assets/tpl1724919447239.png
autoansign/assets/tpl1724919477621.png
autoansign/assets/tpl1725544480761.png
autoansign/assets/tpl1725544488815.png
autoansign/assets/tpl1725544509798.png
autoansign/assets/tpl1730443076289.png
autoansign/assets/tpl1751264596196.png
autoansign/assets/tpl1751264772613.png
autoansign/assets/tpl1751265051281.png
autoansign-1.2.1.dist-info/licenses/LICENSE
autoansign-1.2.1.dist-info/METADATA
autoansign-1.2.1.dist-info/WHEEL
autoansign-1.2.1.dist-info/entry_points.txt
autoansign-1.2.1.dist-info/top_level.txt
autoansign-1.2.1.dist-info/RECORD
